llm_fragments_markitdown.py
llm_fragments_markitdown-0.1.0.dist-info/METADATA
llm_fragments_markitdown-0.1.0.dist-info/WHEEL
llm_fragments_markitdown-0.1.0.dist-info/entry_points.txt
llm_fragments_markitdown-0.1.0.dist-info/licenses/LICENSE
llm_fragments_markitdown-0.1.0.dist-info/RECORD
