Metadata-Version: 2.4
Name: llm-fragments-markitdown
Version: 0.1.0
Summary: LLM fragment loader which converts various formats to Markdown.
Project-URL: Homepage, https://github.com/wolfmanstout/llm-fragments-markitdown
Project-URL: Changelog, https://github.com/wolfmanstout/llm-fragments-markitdown/releases
Project-URL: Issues, https://github.com/wolfmanstout/llm-fragments-markitdown/issues
Project-URL: CI, https://github.com/wolfmanstout/llm-fragments-markitdown/actions
Author: James Stout
License-File: LICENSE
Classifier: License :: OSI Approved :: Apache Software License
Requires-Python: >=3.11
Requires-Dist: llm
Requires-Dist: markitdown
